
{
    "categories": [
      { "id": 1, "name": "Category 1" },
      { "id": 2, "name": "Category 2" },
      { "id": 3, "name": "Category 3" }
    ],
    "products": [
      {
        "id": 1,
        "categoryId": 1,
        "name": "Product 1",
        "price": 10.99,
        "imageUrl": "https://example.com/product1.jpg",
        "description": "Description of Product 1"
      },
      {
        "id": 2,
        "categoryId": 1,
        "name": "Product 2",
        "price": 12.99,
        "imageUrl": "https://example.com/product2.jpg",
        "description": "Description of Product 2"
      },
      {
        "id": 3,
        "categoryId": 2,
        "name": "Product 3",
        "price": 8.99,
        "imageUrl": "https://example.com/product3.jpg",
        "description": "Description of Product 3"
      },
      {
        "id": 4,
        "categoryId": 3,
        "name": "Product 4",
        "price": 13.99,
        "imageUrl": "https://example.com/product4.jpg",
        "description": "Description of Product 4"
      },
      {
        "id": 5,
        "categoryId": 1,
        "name": "Product 5",
        "price": 0.99,
        "imageUrl": "https://example.com/product4.jpg",
        "description": "Description of Product 5"
      }
    ]
  }